maelzel/.gitignore
maelzel/__init__.py
maelzel/_imgtools.py
maelzel/_indentedwriter.py
maelzel/_logutils.py
maelzel/_result.py
maelzel/_state.py
maelzel/_util.py
maelzel/colortheory.py
maelzel/common.py
maelzel/dependencies.py
maelzel/distribute.py
maelzel/dynamiccurve.py
maelzel/histogram.py
maelzel/mathutils.py
maelzel/mpqfractions.py
maelzel/packing.py
maelzel/pitchtoolsnp.py
maelzel/py.typed
maelzel/rational.py
maelzel/scorestruct.py
maelzel/stats.py
maelzel/textstyle.py
maelzel/tui.py
maelzel/acoustics/__init__.py
maelzel/acoustics/helmholtz.py
maelzel/acoustics/psycoacoustics.py
maelzel/acoustics/soundlevel.py
maelzel/acoustics/soundspeed.py
maelzel/acoustics/tubes.py
maelzel/core/__init__.py
maelzel/core/_appstate.py
maelzel/core/_common.py
maelzel/core/_configtools.py
maelzel/core/_dialogs.py
maelzel/core/_eventutils.py
maelzel/core/_lazyapi.py
maelzel/core/_mobjtools.py
maelzel/core/_playbacktools.py
maelzel/core/_ringmodchord.py
maelzel/core/_tools.py
maelzel/core/_typedefs.py
maelzel/core/automation.py
maelzel/core/builtinpresets.py
maelzel/core/chain.py
maelzel/core/clicktrack.py
maelzel/core/clip.py
maelzel/core/config.py
maelzel/core/configdata.py
maelzel/core/environment.py
maelzel/core/errors.py
maelzel/core/event.py
maelzel/core/eventbase.py
maelzel/core/interactive.py
maelzel/core/jupytertools.py
maelzel/core/mevent.py
maelzel/core/mobj.py
maelzel/core/mobjlist.py
maelzel/core/musicxmlparser.py
maelzel/core/notation.py
maelzel/core/offline.py
maelzel/core/playback.py
maelzel/core/plotting.py
maelzel/core/presetdef.py
maelzel/core/presetmanager.py
maelzel/core/presetutils.py
maelzel/core/proxysynth.py
maelzel/core/py.typed
maelzel/core/realtimerenderer.py
maelzel/core/renderer.py
maelzel/core/score.py
maelzel/core/shortcuts.py
maelzel/core/symbols.py
maelzel/core/synthevent.py
maelzel/core/workspace.py
maelzel/data/Bravura.otf
maelzel/data/sf2/SalC5Light2.sf2
maelzel/data/vamp/linux-x86_64/pyin.cat
maelzel/data/vamp/linux-x86_64/pyin.n3
maelzel-1.10.0.dist-info/licenses/LICENSE.md
maelzel-1.10.0.dist-info/METADATA
maelzel-1.10.0.dist-info/WHEEL
maelzel-1.10.0.dist-info/top_level.txt
maelzel-1.10.0.dist-info/RECORD
