Metadata-Version: 2.4
Name: maelzel
Version: 1.10.0
Summary: Framework for computer music and composition
Author-email: Eduardo Moguillansky <eduardo.moguillansky@gmail.com>
License:                     GNU GENERAL PUBLIC LICENSE
Project-URL: Homepage, https://github.com/gesellkammer/maelzel
Classifier: Programming Language :: Python :: 3
Classifier: Operating System :: OS Independent
Classifier: Topic :: Multimedia :: Sound/Audio
Requires-Python: >=3.12
License-File: LICENSE.md
Requires-Dist: numpy
Requires-Dist: scipy
Requires-Dist: matplotlib
Requires-Dist: appdirs
Requires-Dist: tabulate
Requires-Dist: cachetools
Requires-Dist: pyyaml
Requires-Dist: psutil
Requires-Dist: lxml
Requires-Dist: quicktions
Requires-Dist: rich
Requires-Dist: chardet
Requires-Dist: simple-term-menu
Requires-Dist: visvalingamwyatt
Requires-Dist: pybase64
Requires-Dist: thefuzz
Requires-Dist: soxr
Requires-Dist: python-constraint
Requires-Dist: pillow<11
Requires-Dist: sounddevice
Requires-Dist: typing_extensions
Requires-Dist: imagesize
Requires-Dist: pypng
Requires-Dist: emlib>=1.20.0
Requires-Dist: libcsound>=0.10.8
Requires-Dist: bpf4>=1.14.0
Requires-Dist: configdict>=2.13
Requires-Dist: sndfileio>=1.9.1
Requires-Dist: numpyx>=1.4.1
Requires-Dist: csoundengine>=2.21.7
Requires-Dist: pitchtools>=1.16.0
Requires-Dist: risset>=3.2.0
Requires-Dist: loristrck>=1.6.1
Requires-Dist: vamphost>=1.3.0
Requires-Dist: lilyponddist>=1.1.0
Dynamic: license-file
